setup.py
py_lclogger/__init__.py
py_lclogger/logger.py
py_lclogger.egg-info/PKG-INFO
py_lclogger.egg-info/SOURCES.txt
py_lclogger.egg-info/dependency_links.txt
py_lclogger.egg-info/requires.txt
py_lclogger.egg-info/top_level.txt