Metadata-Version: 1.0
Name: py-lclogger
Version: 0.4
Summary: Save log to server
Home-page: http://xiangyang.li/project/python_lclogger
Author: bac
Author-email: wo@xiangyang.li
License: Apache License
Keywords: LogCentral,log,logger
Platform: any
